alea/__init__.py
alea/ces_source.py
alea/ces_transformation.py
alea/examples/__init__.py
alea/examples/configs/binned_ces.yaml
alea/examples/configs/test_cs1_spectrum.json
alea/examples/configs/unbinned_ces_simple.yaml
alea/examples/configs/unbinned_wimp_running.yaml
alea/examples/configs/unbinned_wimp_statistical_model.yaml
alea/examples/configs/unbinned_wimp_statistical_model_index_fitting.yaml
alea/examples/configs/unbinned_wimp_statistical_model_mass_dependent_efficiency.yaml
alea/examples/configs/unbinned_wimp_statistical_model_simple.yaml
alea/examples/configs/unbinned_wimp_statistical_model_template_source_test.yaml
alea/examples/gaussian_model.py
alea/examples/templates/er_template.ii.h5
alea/examples/templates/er_template_-1.ii.h5
alea/examples/templates/er_template_-2.ii.h5
alea/examples/templates/er_template_0.ii.h5
alea/examples/templates/er_template_1.ii.h5
alea/examples/templates/er_template_2.ii.h5
alea/examples/templates/wimp50gev_template.ii.h5
alea/examples/templates/xe133_template.ii.h5
alea/examples/templates/xe136_template.ii.h5
alea/model.py
alea/models/__init__.py
alea/models/blueice_extended_model.py
alea/parameters.py
alea/runner.py
alea/scripts/__init__.py
alea/scripts/alea_run_toymc.py
alea/scripts/alea_submission.py
alea/simulators.py
alea/submitter.py
alea/submitters/.gitignore
alea/submitters/README.md
alea/submitters/__init__.py
alea/submitters/combine.sh
alea/submitters/htcondor.py
alea/submitters/local.py
alea/submitters/run_toymc_wrapper.sh
alea/submitters/separate.sh
alea/submitters/slurm.py
alea/submitters/workflow_example.png
alea/template_source.py
alea/utils.py
alea_inference-0.3.4.dist-info/LICENSE
alea_inference-0.3.4.dist-info/METADATA
alea_inference-0.3.4.dist-info/WHEEL
alea_inference-0.3.4.dist-info/entry_points.txt
alea_inference-0.3.4.dist-info/RECORD
