Metadata-Version: 2.3
Name: alea-inference
Version: 0.3.4
Summary: A tool to perform toyMC-based inference constructions
Author: Alea contributors, the XENON collaboration
Requires-Python: >=3.8,<3.13
Classifier: Development Status :: 4 - Beta
Classifier: Intended Audience :: Science/Research
Classifier: License :: OSI Approved :: BSD License
Classifier: Natural Language :: English
Classifier: Programming Language :: Python :: 3
Classifier: Programming Language :: Python :: 3.8
Classifier: Programming Language :: Python :: 3.9
Classifier: Programming Language :: Python :: 3.10
Classifier: Programming Language :: Python :: 3.11
Classifier: Programming Language :: Python :: 3.12
Classifier: Programming Language :: Python :: Implementation :: CPython
Classifier: Topic :: Scientific/Engineering :: Physics
Provides-Extra: docs
Requires-Dist: Jinja2 (==3.0.3) ; extra == "docs"
Requires-Dist: PyYAML
Requires-Dist: atomicwrites
Requires-Dist: blueice (>=1.2.1)
Requires-Dist: commonmark (==0.9.1) ; extra == "docs"
Requires-Dist: graphviz (==0.20.1) ; extra == "docs"
Requires-Dist: h5py
Requires-Dist: iminuit (>=2.21.0)
Requires-Dist: inference-interface
Requires-Dist: lxml_html_clean ; extra == "docs"
Requires-Dist: m2r (==0.2.1) ; extra == "docs"
Requires-Dist: matplotlib
Requires-Dist: mergedeep
Requires-Dist: mistune (==0.8.4) ; extra == "docs"
Requires-Dist: multihist
Requires-Dist: nbsphinx (==0.8.9) ; extra == "docs"
Requires-Dist: numpy
Requires-Dist: recommonmark (==0.7.1) ; extra == "docs"
Requires-Dist: scipy
Requires-Dist: sphinx (==5.2.3) ; extra == "docs"
Requires-Dist: sphinx_rtd_theme (==1.0.0) ; extra == "docs"
Requires-Dist: tqdm
Requires-Dist: utilix (>=0.11.0)
Project-URL: Repository, https://github.com/XENONnT/alea
